workflows_emulator/__init__.py
workflows_emulator/cli.py
workflows_emulator/discovery_documents/aiplatform_v1.json
workflows_emulator/discovery_documents/batch_v1.json
workflows_emulator/discovery_documents/bigquery_v2.json
workflows_emulator/discovery_documents/bigquerydatatransfer_v1.json
workflows_emulator/discovery_documents/cloudbuild_v1.json
workflows_emulator/discovery_documents/cloudfunctions_v1.json
workflows_emulator/discovery_documents/cloudfunctions_v2.json
workflows_emulator/discovery_documents/cloudresourcemanager_v1.json
workflows_emulator/discovery_documents/cloudresourcemanager_v2.json
workflows_emulator/discovery_documents/cloudresourcemanager_v3.json
workflows_emulator/discovery_documents/cloudscheduler_v1.json
workflows_emulator/discovery_documents/compute_v1.json
workflows_emulator/discovery_documents/container_v1.json
workflows_emulator/discovery_documents/dataflow_v1b3.json
workflows_emulator/discovery_documents/documentai_v1.json
workflows_emulator/discovery_documents/firestore_v1.json
workflows_emulator/discovery_documents/forms_v1.json
workflows_emulator/discovery_documents/integrations_v1.json
workflows_emulator/discovery_documents/language_v1.json
workflows_emulator/discovery_documents/ml_v1.json
workflows_emulator/discovery_documents/pubsub_v1.json
workflows_emulator/discovery_documents/run_v1.json
workflows_emulator/discovery_documents/run_v2.json
workflows_emulator/discovery_documents/secretmanager_v1.json
workflows_emulator/discovery_documents/sheets_v4.json
workflows_emulator/discovery_documents/spanner_v1.json
workflows_emulator/discovery_documents/sqladmin_v1.json
workflows_emulator/discovery_documents/storage_v1.json
workflows_emulator/discovery_documents/storagetransfer_v1.json
workflows_emulator/discovery_documents/transcoder_v1.json
workflows_emulator/discovery_documents/translate_v2.json
workflows_emulator/discovery_documents/workflowexecutions_v1.json
workflows_emulator/discovery_documents/workflows_v1.json
workflows_emulator-1.10.0.dist-info/METADATA
workflows_emulator-1.10.0.dist-info/WHEEL
workflows_emulator-1.10.0.dist-info/entry_points.txt
workflows_emulator-1.10.0.dist-info/RECORD
