Metadata-Version: 2.1
Name: workflows-emulator
Version: 1.10.0
Summary: Google Workflows Emulator and testing utilities
Author: Daniel Iñigo
Author-email: daniel.inigo@datatonic.com
Requires-Python: >=3.10,<4.0
Classifier: Programming Language :: Python :: 3
Classifier: Programming Language :: Python :: 3.10
Classifier: Programming Language :: Python :: 3.11
Classifier: Programming Language :: Python :: 3.12
Classifier: Programming Language :: Python :: 3.13
Requires-Dist: addict (>=2.4.0,<3.0.0)
Requires-Dist: coloredlogs (>=15.0.1,<16.0.0)
Requires-Dist: fastapi (>=0.111.1,<0.112.0)
Requires-Dist: google-auth (>=2.32.0,<3.0.0)
Requires-Dist: google-re2 (>=1.1.20240702,<2.0.0)
Requires-Dist: jinja2 (>=3.1.4,<4.0.0)
Requires-Dist: jsonschema (>=4.23.0,<5.0.0)
Requires-Dist: python-dotenv (>=1.0.1,<2.0.0)
Requires-Dist: pyyaml (>=6.0.1,<7.0.0)
Requires-Dist: requests (>=2.32.3,<3.0.0)
Requires-Dist: typeguard (>=4.3.0,<5.0.0)
